django_puepy/__init__.py
django_puepy/apps.py
django_puepy/config.py
django_puepy/paths.py
django_puepy/puepy_view.py
django_puepy/static/django_puepy/django_backend.py
django_puepy/static/django_puepy/dtjson.py
django_puepy/static/django_puepy/puepy-0.3.7-py3-none-any.whl
django_puepy/templates/django_puepy/puepy_script.html
django_puepy/templates/django_puepy/puepy_view.html
django_puepy/templatetags/__init__.py
django_puepy/templatetags/puepy.py
django_puepy/urls.py
django_puepy-0.1.2.dist-info/LICENSE
django_puepy-0.1.2.dist-info/METADATA
django_puepy-0.1.2.dist-info/WHEEL
django_puepy-0.1.2.dist-info/RECORD
