Metadata-Version: 2.1
Name: django-puepy
Version: 0.1.2
Summary: PuePy integration for Django
License: Apache
Author: Ken Kinder
Author-email: ken+github@kkinder.com
Requires-Python: >=3.11,<4.0
Classifier: License :: Other/Proprietary License
Classifier: Programming Language :: Python :: 3
Classifier: Programming Language :: Python :: 3.11
Requires-Dist: Django (>=5.0.7,<6.0.0)
Requires-Dist: json-dt-serializer (>=1.1.0,<2.0.0)
Requires-Dist: puepy (>=0.3.7,<0.4.0)
